Workbook

Sheet Attendance_May2026
A1: MONTH | B1: YEAR | C1: ="Fully Automatic Attendance Sheet - "&A2&" "&B2 -> Fully Automatic Attendance Sheet - May 2026 | AH1: D&A pvt ltd.
A2: May | B2: 2026
A3: =DATEVALUE("1"&A2&B2) -> 46143 | B3: =EOMONTH(A3,0) -> 46173
A4: Emp_ID | B4: Emp_Name | C4: =A3 -> 46143 | D4: =IF(C4<$B$3,C4+1,"") -> 46144 | E4: =IF(D4<$B$3,D4+1,"") -> 46145 | F4: =IF(E4<$B$3,E4+1,"") -> 46146 | G4: =IF(F4<$B$3,F4+1,"") -> 46147 | H4: =IF(G4<$B$3,G4+1,"") -> 46148 | I4: =IF(H4<$B$3,H4+1,"") -> 46149 | J4: =IF(I4<$B$3,I4+1,"") -> 46150 | K4: =IF(J4<$B$3,J4+1,"") -> 46151 | ... AG4: =IF(AF4<$B$3,AF4+1,"") -> 46173 | AH4: Total Days | AI4: Present | AJ4: Absent | AK4: Holiday | AL4: Week Off | AM4: SL | AN4: CL
C5: =TEXT(C4,"DDD") -> Fri | D5: =TEXT(D4,"DDD") -> Sat | E5: =TEXT(E4,"DDD") -> Sun | F5: =TEXT(F4,"DDD") -> Mon | G5: =TEXT(G4,"DDD") -> Tue | H5: =TEXT(H4,"DDD") -> Wed | I5: =TEXT(I4,"DDD") -> Thu | J5: =TEXT(J4,"DDD") -> Fri | ... AG5: =TEXT(AG4,"DDD") -> Sun
A7: EMP001 | B7: Aarav Sharma | C7: h | D7: p | F7: p | G7: a | H7: p | I7: p | J7: p | K7: p | M7: p | N7: p | O7: p | P7: p | Q7: p | R7: h | T7: p | U7: a | V7: p | W7: p | X7: p | Y7: p | AA7: p | AB7: h | AC7: p | AD7: p | AE7: p | AF7: sl | AH7: =COUNT(C$4:AG$4) -> 31 | AI7: =COUNTIF($C7:$AG7,"p") -> 20 | AJ7: =COUNTIF($C7:$AG7,"a") -> 2 | AK7: =COUNTIF($C7:$AG7,"h") -> 3 | AL7: =COUNTIF(C$5:AG$6,"sun") -> 5 | AM7: =COUNTIF($C7:$AG7,"sl") -> 1 | AN7: =COUNTIF($C7:$AG7,"cl") -> 0
A8: EMP002 | B8: Ananya Iyer | C8: h | D8: p | F8: p | G8: p | H8: p | I8: p | J8: a | K8: p | M8: p | N8: p | O8: p | P8: p | Q8: p | R8: h | T8: p | U8: p | V8: p | W8: p | X8: p | Y8: p | AA8: p | AB8: h | AC8: p | AD8: p | AE8: p | AF8: p | AH8: =COUNT(C$4:AG$4) -> 31 | AI8: =COUNTIF($C8:$AG8,"p") -> 22 | AJ8: =COUNTIF($C8:$AG8,"a") -> 1 | AK8: =COUNTIF($C8:$AG8,"h") -> 3 | AL8: =COUNTIF(C$5:AG$6,"sun") -> 5 | AM8: =COUNTIF($C8:$AG8,"sl") -> 0 | AN8: =COUNTIF($C8:$AG8,"cl") -> 0
A9: EMP003 | B9: Ishaan Kapoor | C9: h | D9: p | F9: p | G9: a | H9: p | I9: p | J9: p | K9: p | M9: p | N9: a | O9: sl | P9: p | Q9: p | R9: h | T9: p | U9: p | V9: a | W9: p | X9: p | Y9: p | AA9: p | AB9: h | AC9: p | AD9: p | AE9: p | AF9: p | AH9: =COUNT(C$4:AG$4) -> 31 | AI9: =COUNTIF($C9:$AG9,"p") -> 19 | AJ9: =COUNTIF($C9:$AG9,"a") -> 3 | AK9: =COUNTIF($C9:$AG9,"h") -> 3 | AL9: =COUNTIF(C$5:AG$6,"sun") -> 5 | AM9: =COUNTIF($C9:$AG9,"sl") -> 1 | AN9: =COUNTIF($C9:$AG9,"cl") -> 0
A10: EMP004 | B10: Diya Nair | C10: h | D10: p | F10: p | G10: p | H10: p | I10: p | J10: p | K10: a | M10: p | N10: p | O10: p | P10: p | Q10: p | R10: h | T10: p | U10: p | V10: p | W10: p | X10: p | Y10: a | AA10: p | AB10: h | AC10: p | AD10: sl | AE10: p | AF10: p | AH10: =COUNT(C$4:AG$4) -> 31 | AI10: =COUNTIF($C10:$AG10,"p") -> 20 | AJ10: =COUNTIF($C10:$AG10,"a") -> 2 | AK10: =COUNTIF($C10:$AG10,"h") -> 3 | AL10: =COUNTIF(C$5:AG$6,"sun") -> 5 | AM10: =COUNTIF($C10:$AG10,"sl") -> 1 | AN10: =COUNTIF($C10:$AG10,"cl") -> 0
A11: EMP005 | B11: Rohan Deshmukh | C11: h | D11: p | F11: p | G11: p | H11: p | I11: p | J11: a | K11: p | M11: p | N11: p | O11: p | P11: p | Q11: a | R11: h | T11: p | U11: p | V11: p | W11: cl | X11: p | Y11: p | AA11: p | AB11: h | AC11: p | AD11: p | AE11: p | AF11: p | AH11: =COUNT(C$4:AG$4) -> 31 | AI11: =COUNTIF($C11:$AG11,"p") -> 20 | AJ11: =COUNTIF($C11:$AG11,"a") -> 2 | AK11: =COUNTIF($C11:$AG11,"h") -> 3 | AL11: =COUNTIF(C$5:AG$6,"sun") -> 5 | AM11: =COUNTIF($C11:$AG11,"sl") -> 0 | AN11: =COUNTIF($C11:$AG11,"cl") -> 1
A12: EMP006 | B12: Meera Banerjee | C12: h | D12: p | F12: p | G12: p | H12: a | I12: p | J12: p | K12: p | M12: p | N12: p | O12: p | P12: p | Q12: p | R12: h | T12: a | U12: p | V12: p | W12: p | X12: p | Y12: p | AA12: p | AB12: h | AC12: p | AD12: p | AE12: p | AF12: p | AH12: =COUNT(C$4:AG$4) -> 31 | AI12: =COUNTIF($C12:$AG12,"p") -> 21 | AJ12: =COUNTIF($C12:$AG12,"a") -> 2 | AK12: =COUNTIF($C12:$AG12,"h") -> 3 | AL12: =COUNTIF(C$5:AG$6,"sun") -> 5 | AM12: =COUNTIF($C12:$AG12,"sl") -> 0 | AN12: =COUNTIF($C12:$AG12,"cl") -> 0
A13: EMP007 | B13: Arjun Verma | C13: h | D13: p | F13: sl | G13: p | H13: p | I13: p | J13: p | K13: p | M13: p | N13: p | O13: a | P13: p | Q13: p | R13: h | T13: p | U13: p | V13: p | W13: p | X13: p | Y13: p | AA13: p | AB13: h | AC13: p | AD13: p | AE13: p | AF13: p | AH13: =COUNT(C$4:AG$4) -> 31 | AI13: =COUNTIF($C13:$AG13,"p") -> 21 | AJ13: =COUNTIF($C13:$AG13,"a") -> 1 | AK13: =COUNTIF($C13:$AG13,"h") -> 3 | AL13: =COUNTIF(C$5:AG$6,"sun") -> 5 | AM13: =COUNTIF($C13:$AG13,"sl") -> 1 | AN13: =COUNTIF($C13:$AG13,"cl") -> 0
A14: EMP008 | B14: Kavya Reddy | C14: h | D14: p | F14: p | G14: p | H14: p | I14: p | J14: p | K14: p | M14: p | N14: p | O14: cl | P14: p | Q14: p | R14: h | T14: p | U14: a | V14: p | W14: p | X14: p | Y14: p | AA14: p | AB14: h | AC14: sl | AD14: p | AE14: p | AF14: p | AH14: =COUNT(C$4:AG$4) -> 31 | AI14: =COUNTIF($C14:$AG14,"p") -> 20 | AJ14: =COUNTIF($C14:$AG14,"a") -> 1 | AK14: =COUNTIF($C14:$AG14,"h") -> 3 | AL14: =COUNTIF(C$5:AG$6,"sun") -> 5 | AM14: =COUNTIF($C14:$AG14,"sl") -> 1 | AN14: =COUNTIF($C14:$AG14,"cl") -> 1
A15: EMP009 | B15: Kabir Joshi | C15: h | D15: p | F15: p | G15: p | H15: p | I15: cl | J15: p | K15: p | M15: p | N15: p | O15: p | P15: p | Q15: p | R15: h | T15: p | U15: p | V15: p | W15: p | X15: p | Y15: a | AA15: p | AB15: h | AC15: p | AD15: p | AE15: p | AF15: p | AH15: =COUNT(C$4:AG$4) -> 31 | AI15: =COUNTIF($C15:$AG15,"p") -> 21 | AJ15: =COUNTIF($C15:$AG15,"a") -> 1 | AK15: =COUNTIF($C15:$AG15,"h") -> 3 | AL15: =COUNTIF(C$5:AG$6,"sun") -> 5 | AM15: =COUNTIF($C15:$AG15,"sl") -> 0 | AN15: =COUNTIF($C15:$AG15,"cl") -> 1
A16: EMP010 | B16: Anika Choudhury | C16: h | D16: p | F16: p | G16: p | H16: p | I16: p | J16: p | K16: p | M16: a | N16: p | O16: p | P16: p | Q16: p | R16: h | T16: p | U16: p | V16: sl | W16: p | X16: p | Y16: p | AA16: p | AB16: h | AC16: p | AD16: p | AE16: p | AF16: p | AH16: =COUNT(C$4:AG$4) -> 31 | AI16: =COUNTIF($C16:$AG16,"p") -> 21 | AJ16: =COUNTIF($C16:$AG16,"a") -> 1 | AK16: =COUNTIF($C16:$AG16,"h") -> 3 | AL16: =COUNTIF(C$5:AG$6,"sun") -> 5 | AM16: =COUNTIF($C16:$AG16,"sl") -> 1 | AN16: =COUNTIF($C16:$AG16,"cl") -> 0
A17: EMP011 | B17: Devendra Kulkarni | C17: h | D17: p | F17: p | G17: p | H17: a | I17: p | J17: p | K17: p | M17: p | N17: p | O17: p | P17: p | Q17: p | R17: h | T17: p | U17: p | V17: p | W17: p | X17: p | Y17: p | AA17: p | AB17: h | AC17: p | AD17: p | AE17: sl | AF17: p | AH17: =COUNT(C$4:AG$4) -> 31 | AI17: =COUNTIF($C17:$AG17,"p") -> 21 | AJ17: =COUNTIF($C17:$AG17,"a") -> 1 | AK17: =COUNTIF($C17:$AG17,"h") -> 3 | AL17: =COUNTIF(C$5:AG$6,"sun") -> 5 | AM17: =COUNTIF($C17:$AG17,"sl") -> 1 | AN17: =COUNTIF($C17:$AG17,"cl") -> 0
A18: EMP012 | B18: Riya Chatterjee | C18: h | D18: p | F18: p | G18: p | H18: p | I18: p | J18: p | K18: p | M18: a | N18: p | O18: p | P18: p | Q18: p | R18: h | T18: p | U18: p | V18: p | W18: p | X18: a | Y18: p | AA18: p | AB18: h | AC18: p | AD18: p | AE18: p | AF18: p | AH18: =COUNT(C$4:AG$4) -> 31 | AI18: =COUNTIF($C18:$AG18,"p") -> 21 | AJ18: =COUNTIF($C18:$AG18,"a") -> 2 | AK18: =COUNTIF($C18:$AG18,"h") -> 3 | AL18: =COUNTIF(C$5:AG$6,"sun") -> 5 | AM18: =COUNTIF($C18:$AG18,"sl") -> 0 | AN18: =COUNTIF($C18:$AG18,"cl") -> 0
... A21: EMP015 | B21: Vivaan Mehta | C21: h | D21: p | F21: p | G21: p | H21: a | I21: p | J21: p | K21: p | M21: p | N21: p | O21: p | P21: p | Q21: a | R21: h | T21: p | U21: p | V21: p | W21: p | X21: p | Y21: sl | AA21: p | AB21: h | AC21: p | AD21: p | AE21: p | AF21: p | AH21: =COUNT(C$4:AG$4) -> 31 | AI21: =COUNTIF($C21:$AG21,"p") -> 20 | AJ21: =COUNTIF($C21:$AG21,"a") -> 2 | AK21: =COUNTIF($C21:$AG21,"h") -> 3 | AL21: =COUNTIF(C$5:AG$6,"sun") -> 5 | AM21: =COUNTIF($C21:$AG21,"sl") -> 1 | AN21: =COUNTIF($C21:$AG21,"cl") -> 0

Sheet Salary_Sheet
A1: =Attendance_May2026!C1 -> Fully Automatic Attendance Sheet - May 2026 | P1: =Attendance_May2026!AH1 -> D&A pvt ltd.
A4: Emp_ID | B4: EMP_Name | C4: Designation | D4: Basic Salary | E4: Total Days | F4: Attendance(Working Days) | G4: Per Day Salary | H4: Salary (Based on Attendance) | I4: DA (12%) | J4: City | K4: HRA | L4: TA | M4: OT in Hrs. | N4: Overtime Pay | O4: Gross Salary | P4: PF (12%) | Q4: ESI (0.75%) | R4: Net Salary
A5: EMP001 | B5: Aarav Sharma | C5: Manager | D5: 30000 | E5: =Attendance_May2026!AH7 -> 31 | F5: =Attendance_May2026!AI7 -> 20 | G5: =D5/E5 -> 967.74194 | H5: =G5*F5 -> 19354.839 | I5: =D5*12% -> 3600 | J5: Metro | K5: =IF(J5="Metro",D5*50%,D5*40%) -> 15000 | L5: 1000 | M5: 10 | N5: =G5/8*M5 -> 1209.6774 | O5: =H5+I5+K5+L5+N5 -> 40164.516 | P5: =D5*12% -> 3600 | Q5: =IF(O5<=21000,O5*0.75%,"N/A") -> N/A | R5: =IF(ISNUMBER(Q5),O5-P5-Q5,O5-P5) -> 36564.516
A6: EMP002 | B6: Ananya Iyer | C6: Engineer | D6: 25000 | E6: =Attendance_May2026!AH8 -> 31 | F6: =Attendance_May2026!AI8 -> 22 | G6: =D6/E6 -> 806.45161 | H6: =G6*F6 -> 17741.935 | I6: =D6*12% -> 3000 | J6: Non-Metro | K6: =IF(J6="Metro",D6*50%,D6*40%) -> 10000 | L6: 2000 | M6: 15 | N6: =G6/8*M6 -> 1512.0968 | O6: =H6+I6+K6+L6+N6 -> 34254.032 | P6: =D6*12% -> 3000 | Q6: =IF(O6<=21000,O6*0.75%,"N/A") -> N/A | R6: =IF(ISNUMBER(Q6),O6-P6-Q6,O6-P6) -> 31254.032
A7: EMP003 | B7: Ishaan Kapoor | C7: Supervisor | D7: 18000 | E7: =Attendance_May2026!AH9 -> 31 | F7: =Attendance_May2026!AI9 -> 19 | G7: =D7/E7 -> 580.64516 | H7: =G7*F7 -> 11032.258 | I7: =D7*12% -> 2160 | J7: Metro | K7: =IF(J7="Metro",D7*50%,D7*40%) -> 9000 | L7: 1000 | M7: 20 | N7: =G7/8*M7 -> 1451.6129 | O7: =H7+I7+K7+L7+N7 -> 24643.871 | P7: =D7*12% -> 2160 | Q7: =IF(O7<=21000,O7*0.75%,"N/A") -> N/A | R7: =IF(ISNUMBER(Q7),O7-P7-Q7,O7-P7) -> 22483.871
A8: EMP004 | B8: Diya Nair | C8: S. Tech | D8: 15000 | E8: =Attendance_May2026!AH10 -> 31 | F8: =Attendance_May2026!AI10 -> 20 | G8: =D8/E8 -> 483.87097 | H8: =G8*F8 -> 9677.4194 | I8: =D8*12% -> 1800 | J8: Metro | K8: =IF(J8="Metro",D8*50%,D8*40%) -> 7500 | L8: 3000 | M8: 25 | N8: =G8/8*M8 -> 1512.0968 | O8: =H8+I8+K8+L8+N8 -> 23489.516 | P8: =D8*12% -> 1800 | Q8: =IF(O8<=21000,O8*0.75%,"N/A") -> N/A | R8: =IF(ISNUMBER(Q8),O8-P8-Q8,O8-P8) -> 21689.516
A9: EMP005 | B9: Rohan Deshmukh | C9: S. Tech | D9: 15000 | E9: =Attendance_May2026!AH11 -> 31 | F9: =Attendance_May2026!AI11 -> 20 | G9: =D9/E9 -> 483.87097 | H9: =G9*F9 -> 9677.4194 | I9: =D9*12% -> 1800 | J9: Non-Metro | K9: =IF(J9="Metro",D9*50%,D9*40%) -> 6000 | L9: 2000 | M9: 20 | N9: =G9/8*M9 -> 1209.6774 | O9: =H9+I9+K9+L9+N9 -> 20687.097 | P9: =D9*12% -> 1800 | Q9: =IF(O9<=21000,O9*0.75%,"N/A") -> 155.15323 | R9: =IF(ISNUMBER(Q9),O9-P9-Q9,O9-P9) -> 18731.944
A10: EMP006 | B10: Meera Banerjee | C10: S. Tech | D10: 15000 | E10: =Attendance_May2026!AH12 -> 31 | F10: =Attendance_May2026!AI12 -> 21 | G10: =D10/E10 -> 483.87097 | H10: =G10*F10 -> 10161.29 | I10: =D10*12% -> 1800 | J10: Non-Metro | K10: =IF(J10="Metro",D10*50%,D10*40%) -> 6000 | L10: 1000 | M10: 12 | N10: =G10/8*M10 -> 725.80645 | O10: =H10+I10+K10+L10+N10 -> 19687.097 | P10: =D10*12% -> 1800 | Q10: =IF(O10<=21000,O10*0.75%,"N/A") -> 147.65323 | R10: =IF(ISNUMBER(Q10),O10-P10-Q10,O10-P10) -> 17739.444
A11: EMP007 | B11: Arjun Verma | C11: Tech | D11: 12000 | E11: =Attendance_May2026!AH13 -> 31 | F11: =Attendance_May2026!AI13 -> 21 | G11: =D11/E11 -> 387.09677 | H11: =G11*F11 -> 8129.0323 | I11: =D11*12% -> 1440 | J11: Metro | K11: =IF(J11="Metro",D11*50%,D11*40%) -> 6000 | L11: 3000 | M11: 15 | N11: =G11/8*M11 -> 725.80645 | O11: =H11+I11+K11+L11+N11 -> 19294.839 | P11: =D11*12% -> 1440 | Q11: =IF(O11<=21000,O11*0.75%,"N/A") -> 144.71129 | R11: =IF(ISNUMBER(Q11),O11-P11-Q11,O11-P11) -> 17710.127
A12: EMP008 | B12: Kavya Reddy | C12: Tech | D12: 12000 | E12: =Attendance_May2026!AH14 -> 31 | F12: =Attendance_May2026!AI14 -> 20 | G12: =D12/E12 -> 387.09677 | H12: =G12*F12 -> 7741.9355 | I12: =D12*12% -> 1440 | J12: Non-Metro | K12: =IF(J12="Metro",D12*50%,D12*40%) -> 4800 | L12: 2000 | M12: 25 | N12: =G12/8*M12 -> 1209.6774 | O12: =H12+I12+K12+L12+N12 -> 17191.613 | P12: =D12*12% -> 1440 | Q12: =IF(O12<=21000,O12*0.75%,"N/A") -> 128.9371 | R12: =IF(ISNUMBER(Q12),O12-P12-Q12,O12-P12) -> 15622.676
A13: EMP009 | B13: Kabir Joshi | C13: Tech | D13: 12000 | E13: =Attendance_May2026!AH15 -> 31 | F13: =Attendance_May2026!AI15 -> 21 | G13: =D13/E13 -> 387.09677 | H13: =G13*F13 -> 8129.0323 | I13: =D13*12% -> 1440 | J13: Metro | K13: =IF(J13="Metro",D13*50%,D13*40%) -> 6000 | L13: 1000 | M13: 20 | N13: =G13/8*M13 -> 967.74194 | O13: =H13+I13+K13+L13+N13 -> 17536.774 | P13: =D13*12% -> 1440 | Q13: =IF(O13<=21000,O13*0.75%,"N/A") -> 131.52581 | R13: =IF(ISNUMBER(Q13),O13-P13-Q13,O13-P13) -> 15965.248
A14: EMP010 | B14: Anika Choudhury | C14: Tech | D14: 12000 | E14: =Attendance_May2026!AH16 -> 31 | F14: =Attendance_May2026!AI16 -> 21 | G14: =D14/E14 -> 387.09677 | H14: =G14*F14 -> 8129.0323 | I14: =D14*12% -> 1440 | J14: Metro | K14: =IF(J14="Metro",D14*50%,D14*40%) -> 6000 | L14: 1000 | M14: 10 | N14: =G14/8*M14 -> 483.87097 | O14: =H14+I14+K14+L14+N14 -> 17052.903 | P14: =D14*12% -> 1440 | Q14: =IF(O14<=21000,O14*0.75%,"N/A") -> 127.89677 | R14: =IF(ISNUMBER(Q14),O14-P14-Q14,O14-P14) -> 15485.006
A15: EMP011 | B15: Devendra Kulkarni | C15: Helper | D15: 10000 | E15: =Attendance_May2026!AH17 -> 31 | F15: =Attendance_May2026!AI17 -> 21 | G15: =D15/E15 -> 322.58065 | H15: =G15*F15 -> 6774.1935 | I15: =D15*12% -> 1200 | J15: Metro | K15: =IF(J15="Metro",D15*50%,D15*40%) -> 5000 | L15: 2000 | M15: 22 | N15: =G15/8*M15 -> 887.09677 | O15: =H15+I15+K15+L15+N15 -> 15861.29 | P15: =D15*12% -> 1200 | Q15: =IF(O15<=21000,O15*0.75%,"N/A") -> 118.95968 | R15: =IF(ISNUMBER(Q15),O15-P15-Q15,O15-P15) -> 14542.331
A16: EMP012 | B16: Riya Chatterjee | C16: Helper | D16: 10000 | E16: =Attendance_May2026!AH18 -> 31 | F16: =Attendance_May2026!AI18 -> 21 | G16: =D16/E16 -> 322.58065 | H16: =G16*F16 -> 6774.1935 | I16: =D16*12% -> 1200 | J16: Non-Metro | K16: =IF(J16="Metro",D16*50%,D16*40%) -> 4000 | L16: 2000 | M16: 23 | N16: =G16/8*M16 -> 927.41935 | O16: =H16+I16+K16+L16+N16 -> 14901.613 | P16: =D16*12% -> 1200 | Q16: =IF(O16<=21000,O16*0.75%,"N/A") -> 111.7621 | R16: =IF(ISNUMBER(Q16),O16-P16-Q16,O16-P16) -> 13589.851
... A19: EMP015 | B19: Vivaan Mehta | C19: S. Tech | D19: 15000 | E19: =Attendance_May2026!AH21 -> 31 | F19: =Attendance_May2026!AI21 -> 20 | G19: =D19/E19 -> 483.87097 | H19: =G19*F19 -> 9677.4194 | I19: =D19*12% -> 1800 | J19: Metro | K19: =IF(J19="Metro",D19*50%,D19*40%) -> 7500 | L19: 1000 | M19: 25 | N19: =G19/8*M19 -> 1512.0968 | O19: =H19+I19+K19+L19+N19 -> 21489.516 | P19: =D19*12% -> 1800 | Q19: =IF(O19<=21000,O19*0.75%,"N/A") -> N/A | R19: =IF(ISNUMBER(Q19),O19-P19-Q19,O19-P19) -> 19689.516

Sheet Salary_Slip
A1: =Attendance_May2026!AH1 -> D&A pvt ltd.
A2: New Friends Colony, Topsia Kolkata, India-700049
A3: Salary Slip For The Month Of - | D3: =Attendance_May2026!A2 -> May
A4: =Attendance_May2026!B2 -> 2026
A5: Employee Details | C5: Salary Details
A6: Emp_ID | B6: EMP003 | C6: Total Days | D6: =VLOOKUP($B$6,Salary_Sheet!$A$1:$R$19,MATCH(Salary_Slip!$C6,Salary_Sheet!$A$4:$R$4,0),FALSE) -> 31
A7: Emp_Name | B7: =VLOOKUP($B$6,Salary_Sheet!$A$1:$R$19,MATCH(Salary_Slip!$A$7,Salary_Sheet!$A$4:$R$4,0),FALSE) -> Ishaan Kapoor | C7: Attendance(Working Days) | D7: =VLOOKUP($B$6,Salary_Sheet!$A$1:$R$19,MATCH(Salary_Slip!$C7,Salary_Sheet!$A$4:$R$4,0),FALSE) -> 19
A8: Designation | B8: =VLOOKUP($B$6,Salary_Sheet!$A$1:$R$19,MATCH(Salary_Slip!A$8,Salary_Sheet!$A$4:$R$4,0),FALSE) -> Supervisor | C8: Salary Slip Print Date | D8: =TODAY() -> 46181
A10: Basic Salary | C10: =VLOOKUP($B6,Salary_Sheet!$A1:$R19,MATCH(Salary_Slip!$A10,Salary_Sheet!$A4:$R4,0),FALSE) -> 18000 | D10: =VLOOKUP($BJ$6,$AP$1:$BG$19,MATCH(C10,$AP$4:$BG$4,0),FALSE) -> #N/A
A12: Earnings | C12: Deductions
A13: Salary (Based on Attendance) | B13: =VLOOKUP($B$6,Salary_Sheet!$A$1:$R$19,MATCH(Salary_Slip!$A$13,Salary_Sheet!$A$4:$R$4,0),FALSE) -> 11032.258 | C13: PF (12%) | D13: =VLOOKUP($B$6,Salary_Sheet!$A$1:$R$19,MATCH(Salary_Slip!$C13,Salary_Sheet!$A$4:$R$4,0),FALSE) -> 2160
A14: DA (12%) | B14: =VLOOKUP($B$6,Salary_Sheet!A1:R19,MATCH(Salary_Slip!$A$14,Salary_Sheet!$A$4:$R$4,0),FALSE) -> 2160 | C14: ESI (0.75%) | D14: =VLOOKUP($B$6,Salary_Sheet!$A$1:$R$19,MATCH(Salary_Slip!$C14,Salary_Sheet!$A$4:$R$4,0),FALSE) -> N/A
A15: HRA | B15: =VLOOKUP($B$6,Salary_Sheet!$A$1:$R$19,MATCH(Salary_Slip!$A$15,Salary_Sheet!$A$4:$R$4,0),FALSE) -> 9000 | C15: Loan | D15: =IFERROR(VLOOKUP($BJ$6,$AP$1:$BG$19,MATCH($BK$15,$AP$4:$BG$4,0),FALSE),0) -> 0
A16: TA | B16: =VLOOKUP($B$6,Salary_Sheet!$A$1:$R$19,MATCH(Salary_Slip!$A16,Salary_Sheet!$A$4:$R$4,0),FALSE) -> 1000 | C16: Tax | D16: =IFERROR(VLOOKUP($BJ$6,$AP$1:$BG$19,MATCH($BK$16,$AP$4:$BG$4,0),FALSE),0) -> 0
A17: Overtime Pay | B17: =VLOOKUP($B$6,Salary_Sheet!$A$1:$R$19,MATCH(Salary_Slip!$A17,Salary_Sheet!$A$4:$R$4,0),FALSE) -> 1451.6129
A18: Gross Salary | B18: =VLOOKUP($B$6,Salary_Sheet!$A$1:$R$19,MATCH(Salary_Slip!$A18,Salary_Sheet!$A$4:$R$4,0),FALSE) -> 24643.871 | C18: Gross Deduction | D18: =SUM(D13:D16) -> 2160
A20: Net Salary | C20: =B18-D18 -> 22483.871
A22: Employee Signature | C22: Manager Signature
A23: Thank You,
